CHANGELOG.md
LICENSE.md
MANIFEST.in
README.md
requirements.txt
setup.py
./CHANGELOG.md
./LICENSE.md
./README.md
./requirements.txt
./setup.py
./Retro3D/Camera.py
./Retro3D/ConfigGame.py
./Retro3D/Engine.py
./Retro3D/Game.py
./Retro3D/LightDirectional.py
./Retro3D/Matrix.py
./Retro3D/Model.py
./Retro3D/ObjFile.py
./Retro3D/Object.py
./Retro3D/Projection.py
./Retro3D/Rez.py
./Retro3D/__init__.py
./Retro3D/main.py
./Retro3D.egg-info/SOURCES.txt
./Retro3D.egg-info/dependency_links.txt
./Retro3D.egg-info/requires.txt
./Retro3D.egg-info/top_level.txt
./Retro3D/rez/fonts/EternalLogo.ttf
./Retro3D/si/SiDirection.py
./Retro3D/si/SiLog.py
./Retro3D/si/SiRandom.py
./Retro3D/si/SiSystem.py
./Retro3D/si/SiTimer.py
./Retro3D/si/__init__.py
Retro3D/Camera.py
Retro3D/ConfigGame.py
Retro3D/Engine.py
Retro3D/Game.py
Retro3D/LightDirectional.py
Retro3D/Matrix.py
Retro3D/Model.py
Retro3D/ObjFile.py
Retro3D/Object.py
Retro3D/Projection.py
Retro3D/Rez.py
Retro3D/__init__.py
Retro3D/main.py
Retro3D.egg-info/PKG-INFO
Retro3D.egg-info/SOURCES.txt
Retro3D.egg-info/dependency_links.txt
Retro3D.egg-info/requires.txt
Retro3D.egg-info/top_level.txt
Retro3D/rez/fonts/EternalLogo.ttf
Retro3D/si/SiDirection.py
Retro3D/si/SiLog.py
Retro3D/si/SiRandom.py
Retro3D/si/SiSystem.py
Retro3D/si/SiTimer.py
Retro3D/si/__init__.py