Metadata-Version: 2.1
Name: Retro3D
Version: 2.7
Summary: 3D Game Engine with software rendering written in Python
Home-page: UNKNOWN
Author: Deepak Deo
Author-email: deepakbr14@yahoo.com
License: MIT
Keywords: 3d game engine software rendering python
Platform: UNKNOWN
Classifier: Development Status :: 5 - Production/Stable
Classifier: Intended Audience :: Developers
Classifier: Operating System :: OS Independent
Classifier: License :: OSI Approved :: MIT License
Classifier: Programming Language :: Python :: 3
License-File: LICENSE.md
